deasy_client/__init__.py
deasy_client/_base_client.py
deasy_client/_client.py
deasy_client/_compat.py
deasy_client/_constants.py
deasy_client/_exceptions.py
deasy_client/_files.py
deasy_client/_models.py
deasy_client/_qs.py
deasy_client/_resource.py
deasy_client/_response.py
deasy_client/_streaming.py
deasy_client/_types.py
deasy_client/_version.py
deasy_client/py.typed
deasy_client/_utils/__init__.py
deasy_client/_utils/_logs.py
deasy_client/_utils/_proxy.py
deasy_client/_utils/_reflection.py
deasy_client/_utils/_resources_proxy.py
deasy_client/_utils/_streams.py
deasy_client/_utils/_sync.py
deasy_client/_utils/_transform.py
deasy_client/_utils/_typing.py
deasy_client/_utils/_utils.py
deasy_client/lib/.keep
deasy_client/resources/__init__.py
deasy_client/resources/classify.py
deasy_client/resources/classify_bulk.py
deasy_client/resources/deasy_select.py
deasy_client/resources/document_text.py
deasy_client/resources/llm_connector.py
deasy_client/resources/metadata.py
deasy_client/resources/ocr.py
deasy_client/resources/prepare_data.py
deasy_client/resources/schema.py
deasy_client/resources/suggest_description.py
deasy_client/resources/suggest_schema.py
deasy_client/resources/tags.py
deasy_client/resources/task_status.py
deasy_client/resources/vdb_connector.py
deasy_client/resources/dataslice/__init__.py
deasy_client/resources/dataslice/dataslice.py
deasy_client/resources/dataslice/export.py
deasy_client/types/__init__.py
deasy_client/types/classify_bulk_classify_params.py
deasy_client/types/classify_bulk_classify_response.py
deasy_client/types/classify_classify_files_params.py
deasy_client/types/classify_classify_files_response.py
deasy_client/types/condition_input_param.py
deasy_client/types/condition_output.py
deasy_client/types/connector_response.py
deasy_client/types/dataslice_create_params.py
deasy_client/types/dataslice_create_response.py
deasy_client/types/dataslice_delete_params.py
deasy_client/types/dataslice_delete_response.py
deasy_client-0.1.0a45.dist-info/METADATA
deasy_client-0.1.0a45.dist-info/WHEEL
deasy_client-0.1.0a45.dist-info/licenses/LICENSE
deasy_client-0.1.0a45.dist-info/RECORD
